ularkotak/__init__.py
ularkotak/game.py
ularkotak-0.1.0.dist-info/LICENSE
ularkotak-0.1.0.dist-info/METADATA
ularkotak-0.1.0.dist-info/WHEEL
ularkotak-0.1.0.dist-info/top_level.txt
ularkotak-0.1.0.dist-info/RECORD
